lsdir/__init__.py
lsdir/__main__.py
lsdir/lsdir.py
lsdir-0.1.6.dist-info/METADATA
lsdir-0.1.6.dist-info/WHEEL
lsdir-0.1.6.dist-info/entry_points.txt
lsdir-0.1.6.dist-info/top_level.txt
lsdir-0.1.6.dist-info/RECORD
