Metadata-Version: 2.1
Name: lsdir
Version: 0.1.6
Summary: Add your description here
Author-email: "Noah J. Blair" <noahjblair@outlook.com>
Requires-Python: >=3.13
Requires-Dist: python-magic>=0.4.27
